partigraph/__init__.py
partigraph/partition.py
partigraph/spanning_tree.py
partigraph/ust.py
partigraph-0.1.0.dist-info/licenses/LICENSE
partigraph-0.1.0.dist-info/METADATA
partigraph-0.1.0.dist-info/WHEEL
partigraph-0.1.0.dist-info/top_level.txt
partigraph-0.1.0.dist-info/RECORD
