Metadata-Version: 2.4
Name: partigraph
Version: 0.1.0
Summary: Graph partitioning algorithms using random spanning trees
Author-email: Todd Proebsting <proebsting@arizona.edu>
License: MIT
Project-URL: Repository, https://github.com/proebsting/partigraph
Keywords: graph,partition,spanning-tree,redistricting
Classifier: Development Status :: 3 - Alpha
Classifier: Intended Audience :: Developers
Classifier: Intended Audience :: Science/Research
Classifier: License :: OSI Approved :: MIT License
Classifier: Programming Language :: Python :: 3
Classifier: Programming Language :: Python :: 3.12
Classifier: Topic :: Scientific/Engineering :: Mathematics
Requires-Python: >=3.12
License-File: LICENSE
Requires-Dist: networkx
Provides-Extra: docs
Requires-Dist: sphinx>=7.0; extra == "docs"
Requires-Dist: sphinx-rtd-theme; extra == "docs"
Dynamic: license-file
